{
  "name": "Bun (CLI Only)",
  "dockerComposeFile": "../docker-compose.yml",
  "service": "worker",
  "workspaceFolder": "/home/ubuntu/app",
  "remoteUser": "ubuntu",
  "runServices": [
    "meilisearch"
  ],
  "containerEnv": {
    "DISPLAY": "${localEnv:DISPLAY}"
  },
  "features": {
    "ghcr.io/devcontainers/features/common-utils:2": {
      "username": "ubuntu",
      "userUid": "1000",
      "userGid": "1000",
      "installZsh": true,
      "upgradePackages": false
    },
    "ghcr.io/devcontainers/features/node:1": {
      "version": "22",
      "pnpmVersion": "latest"
    },
    "ghcr.io/prulloac/devcontainer-features/bun:1": {
      "version": "latest"
    },
    "ghcr.io/rocker-org/devcontainer-features/apt-packages:1": {
      "packages": "git,wget,curl,ripgrep,xclip,sudo,iputils-ping,procps"
    },
    "ghcr.io/danzilberdan/devcontainers/opencode:0": {},
    "ghcr.io/s1n7ax/devcontainer-features/neovim:2": {}
  },
  "mounts": [
    {
      "source": "${localWorkspaceFolder}/.opencode/auth.json",
      "target": "/mnt/opencode-auth.json",
      "type": "bind"
    }
  ],
  "postCreateCommand": "sudo chown -R ubuntu:ubuntu /home/ubuntu && sudo chown ubuntu:ubuntu /mnt/opencode-auth.json && cd my-app && bun install",
  "forwardPorts": [
    8888
  ]
}
